core_evals/mmath/__init__.py
core_evals/mmath/framework.yml
core_evals/mmath/framework_entrypoint.py
core_evals/mmath/output.py
mmath/__init__.py
mmath/calculate_lcr.py
mmath/callbacks.py
mmath/mmath_eval.py
mmath/utils.py
mmath/mmath/ar.json
mmath/mmath/en.json
mmath/mmath/es.json
mmath/mmath/fr.json
mmath/mmath/ja.json
mmath/mmath/ko.json
mmath/mmath/pt.json
mmath/mmath/th.json
mmath/mmath/vi.json
mmath/mmath/zh.json
nvidia_mmath-25.11.dist-info/licenses/LICENSE
nvidia_mmath-25.11.dist-info/METADATA
nvidia_mmath-25.11.dist-info/WHEEL
nvidia_mmath-25.11.dist-info/entry_points.txt
nvidia_mmath-25.11.dist-info/top_level.txt
nvidia_mmath-25.11.dist-info/RECORD
