Metadata-Version: 2.4
Name: nvidia-mmath
Version: 25.11
Summary: MMATH - packaged by NVIDIA
License: MIT License
Classifier: Development Status :: 5 - Production/Stable
Classifier: Programming Language :: Python :: 3
Classifier: License :: OSI Approved :: MIT License
Classifier: Operating System :: OS Independent
Requires-Python: >=3.10
License-File: LICENSE
Requires-Dist: math-verify==0.7.0
Requires-Dist: tqdm
Requires-Dist: langchain
Requires-Dist: langchain-openai
Requires-Dist: nemo-evaluator
Dynamic: license-file
